VTON/__init__.py
VTON/test.py
VTON/vtons.py
VTON-0.0.2.dist-info/METADATA
VTON-0.0.2.dist-info/WHEEL
VTON-0.0.2.dist-info/top_level.txt
VTON-0.0.2.dist-info/RECORD
